pylove/__init__.py
pylove/lan.py
pylove-1.0.3.dist-info/LICENSE
pylove-1.0.3.dist-info/METADATA
pylove-1.0.3.dist-info/WHEEL
pylove-1.0.3.dist-info/top_level.txt
pylove-1.0.3.dist-info/RECORD
