Metadata-Version: 2.1
Name: pylove
Version: 1.0.3
Summary: A python implementation of the Lovense API
Home-page: https://github.com/catboy1357/pylove
Author: Catboy
Classifier: Programming Language :: Python :: 3
Classifier: License :: OSI Approved :: MIT License
Classifier: Operating System :: OS Independent
License-File: LICENSE
Requires-Dist: requests
